{
	"name": "ds_sn_api_to_adls_csv",
	"properties": {
		"linkedServiceName": {
			"referenceName": "lsADLS",
			"type": "LinkedServiceReference"
		},
		"annotations": [],
		"type": "DelimitedText",
		"typeProperties": {
			"location": {
				"type": "AzureBlobFSLocation",
				"fileName": "api_data.csv",
				"folderPath": "datausa_io_api",
				"fileSystem": "containdestination"
			},
			"columnDelimiter": ",",
			"escapeChar": "\\",
			"firstRowAsHeader": true,
			"quoteChar": "\""
		},
		"schema": []
	}
}